[
    {
        "key": "group_5a9daf44f30b9",
        "title": "Bags Page custom Fields",
        "fields": [
            {
                "key": "field_5a9daf534e0a9",
                "label": "General",
                "name": "",
                "type": "tab",
                "instructions": "",
                "required": 0,
                "conditional_logic": 0,
                "wrapper": {
                    "width": "",
                    "class": "",
                    "id": ""
                },
                "placement": "top",
                "endpoint": 0
            },
            {
                "key": "field_5a9daf704e0aa",
                "label": "Instructions",
                "name": "",
                "type": "message",
                "instructions": "",
                "required": 0,
                "conditional_logic": 0,
                "wrapper": {
                    "width": "",
                    "class": "",
                    "id": ""
                },
                "message": "These are the fields required for the home page broken down by section.\r\nHero Section\r\nSelect Bags to sell",
                "new_lines": "wpautop",
                "esc_html": 0
            },
            {
                "key": "field_5a9dafa44e0ab",
                "label": "Show Hero Section?",
                "name": "show_hero_section",
                "type": "true_false",
                "instructions": "",
                "required": 0,
                "conditional_logic": 0,
                "wrapper": {
                    "width": "",
                    "class": "",
                    "id": ""
                },
                "message": "",
                "default_value": 0,
                "ui": 0,
                "ui_on_text": "",
                "ui_off_text": ""
            },
            {
                "key": "field_5a9dafb44e0ac",
                "label": "Hero Section",
                "name": "",
                "type": "tab",
                "instructions": "",
                "required": 0,
                "conditional_logic": [
                    [
                        {
                            "field": "field_5a9dafa44e0ab",
                            "operator": "==",
                            "value": "1"
                        }
                    ]
                ],
                "wrapper": {
                    "width": "",
                    "class": "",
                    "id": ""
                },
                "placement": "top",
                "endpoint": 0
            },
            {
                "key": "field_5a9dafda4e0ad",
                "label": "Hero First Button Copy",
                "name": "hero_first_button_copy",
                "type": "text",
                "instructions": "",
                "required": 0,
                "conditional_logic": 0,
                "wrapper": {
                    "width": "",
                    "class": "",
                    "id": ""
                },
                "default_value": "",
                "placeholder": "",
                "prepend": "",
                "append": "",
                "maxlength": ""
            },
            {
                "key": "field_5a9db00a4e0ae",
                "label": "Hero First Button URL",
                "name": "hero_first_button_url",
                "type": "url",
                "instructions": "",
                "required": 0,
                "conditional_logic": 0,
                "wrapper": {
                    "width": "",
                    "class": "",
                    "id": ""
                },
                "default_value": "",
                "placeholder": ""
            },
            {
                "key": "field_5a9db0404e0af",
                "label": "Hero Second Button Copy",
                "name": "hero_second_button_copy",
                "type": "text",
                "instructions": "",
                "required": 0,
                "conditional_logic": 0,
                "wrapper": {
                    "width": "",
                    "class": "",
                    "id": ""
                },
                "default_value": "",
                "placeholder": "",
                "prepend": "",
                "append": "",
                "maxlength": ""
            },
            {
                "key": "field_5a9db05d4e0b0",
                "label": "Hero Second Button URL",
                "name": "hero_second_button_url",
                "type": "url",
                "instructions": "",
                "required": 0,
                "conditional_logic": 0,
                "wrapper": {
                    "width": "",
                    "class": "",
                    "id": ""
                },
                "default_value": "",
                "placeholder": ""
            },
            {
                "key": "field_5a9db0774e0b1",
                "label": "Hero Image",
                "name": "hero_image",
                "type": "image",
                "instructions": "",
                "required": 0,
                "conditional_logic": 0,
                "wrapper": {
                    "width": "",
                    "class": "",
                    "id": ""
                },
                "return_format": "array",
                "preview_size": "thumbnail",
                "library": "all",
                "min_width": "",
                "min_height": "",
                "min_size": "",
                "max_width": "",
                "max_height": "",
                "max_size": "",
                "mime_types": ""
            },
            {
                "key": "field_5a9db08b4e0b2",
                "label": "Hero Image (Retina)",
                "name": "hero_image_retina",
                "type": "image",
                "instructions": "",
                "required": 0,
                "conditional_logic": 0,
                "wrapper": {
                    "width": "",
                    "class": "",
                    "id": ""
                },
                "return_format": "array",
                "preview_size": "thumbnail",
                "library": "all",
                "min_width": "",
                "min_height": "",
                "min_size": "",
                "max_width": "",
                "max_height": "",
                "max_size": "",
                "mime_types": ""
            },
            {
                "key": "field_5a9db0974e0b3",
                "label": "Bags Section",
                "name": "",
                "type": "tab",
                "instructions": "",
                "required": 0,
                "conditional_logic": 0,
                "wrapper": {
                    "width": "",
                    "class": "",
                    "id": ""
                },
                "placement": "top",
                "endpoint": 0
            },
            {
                "key": "field_5a9db0a44e0b4",
                "label": "Selectable Bags",
                "name": "selectable_bags",
                "type": "repeater",
                "instructions": "",
                "required": 0,
                "conditional_logic": 0,
                "wrapper": {
                    "width": "",
                    "class": "",
                    "id": ""
                },
                "collapsed": "",
                "min": 0,
                "max": 0,
                "layout": "table",
                "button_label": "",
                "sub_fields": [
                    {
                        "key": "field_5a9db0bb4e0b5",
                        "label": "Product",
                        "name": "product",
                        "type": "post_object",
                        "instructions": "",
                        "required": 0,
                        "conditional_logic": 0,
                        "wrapper": {
                            "width": "",
                            "class": "",
                            "id": ""
                        },
                        "post_type": [
                            "product"
                        ],
                        "taxonomy": [
                            "product_cat:bags"
                        ],
                        "allow_null": 0,
                        "multiple": 0,
                        "return_format": "object",
                        "ui": 1
                    },
                    {
                        "key": "field_5a9db0e24e0b6",
                        "label": "Image Override",
                        "name": "image_override",
                        "type": "image",
                        "instructions": "If you want to use a different image for the product than the default product image. Select it here.",
                        "required": 0,
                        "conditional_logic": 0,
                        "wrapper": {
                            "width": "",
                            "class": "",
                            "id": ""
                        },
                        "return_format": "array",
                        "preview_size": "thumbnail",
                        "library": "all",
                        "min_width": "",
                        "min_height": "",
                        "min_size": "",
                        "max_width": "",
                        "max_height": "",
                        "max_size": "",
                        "mime_types": ""
                    },
                    {
                        "key": "field_5a9db8c500d09",
                        "label": "Image Override (Retina)",
                        "name": "image_override_retina",
                        "type": "image",
                        "instructions": "",
                        "required": 0,
                        "conditional_logic": 0,
                        "wrapper": {
                            "width": "",
                            "class": "",
                            "id": ""
                        },
                        "return_format": "array",
                        "preview_size": "thumbnail",
                        "library": "all",
                        "min_width": "",
                        "min_height": "",
                        "min_size": "",
                        "max_width": "",
                        "max_height": "",
                        "max_size": "",
                        "mime_types": ""
                    }
                ]
            }
        ],
        "location": [
            [
                {
                    "param": "page_template",
                    "operator": "==",
                    "value": "page-bags.php"
                }
            ]
        ],
        "menu_order": 0,
        "position": "normal",
        "style": "default",
        "label_placement": "top",
        "instruction_placement": "label",
        "hide_on_screen": "",
        "active": 1,
        "description": ""
    }
]